setup.py
journalize/__init__.py
journalize.egg-info/PKG-INFO
journalize.egg-info/SOURCES.txt
journalize.egg-info/dependency_links.txt
journalize.egg-info/top_level.txt